<?xml version="1.0"?>
<!DOCTYPE hibernate-mapping PUBLIC "-//Hibernate/Hibernate Mapping DTD 3.0//EN" "http://hibernate.sourceforge.net/hibernate-mapping-3.0.dtd">

<hibernate-mapping>
	
	<sql-query name="getProductsByProductName">
		<return alias="product" class="com.tacton.entity.Product" />
		
<![CDATA[
SELECT *
  FROM tacton.product where product_name= :productName
 
]]>
	</sql-query>
	
	<sql-query name="getCustomerByCustomerId">
		<return alias="customer" class="com.tacton.entity.Customer" />
		
<![CDATA[
SELECT *
  FROM tacton.customer where customer_id= :customerId
 
]]>
	</sql-query>
	
	<sql-query name="getAttributesById">
		<return alias="attribute" class="com.tacton.entity.Attribute" />
		
<![CDATA[
SELECT *
  FROM tacton.attribute where attribute_id= :attributeId
 
]]>
    </sql-query>
    
    <sql-query name="getAllAttributesByType">
		<return alias="attribute" class="com.tacton.entity.Attribute" />
		
<![CDATA[
SELECT *
  FROM tacton.attribute where type= :type
 
]]>
   </sql-query>
   
    <sql-query name="getShoppingCartById">
		<return alias="shopping_cart" class="com.tacton.entity.ShoppingCart" />
		
<![CDATA[
SELECT *
  FROM tacton.shopping_cart where cartid= :cartId and customer_ref_id = :customerId
 
]]>
   </sql-query>
   
   
</hibernate-mapping>